maya-stubs/__init__.pyi
maya-stubs/api/__init__.pyi
maya-stubs/api/MDGContextGuard.pyi
maya-stubs/api/OpenMaya.pyi
maya-stubs/api/OpenMayaAnim.pyi
maya-stubs/api/OpenMayaRender.pyi
maya-stubs/api/OpenMayaUI.pyi
maya-stubs/cmds/__init__.pyi
maya-stubs/mel/__init__.pyi
maya-stubs/OpenMaya.pyi
maya-stubs/OpenMayaAnim.pyi
maya-stubs/OpenMayaFX.pyi
maya-stubs/OpenMayaMPx.pyi
maya-stubs/OpenMayaRender.pyi
maya-stubs/OpenMayaUI.pyi
maya-stubs/standalone.pyi
maya-stubs/utils.pyi
maya_stubs-0.4.1.dist-info/METADATA
maya_stubs-0.4.1.dist-info/WHEEL
maya_stubs-0.4.1.dist-info/RECORD
