Metadata-Version: 2.1
Name: maya-stubs
Version: 0.4.1
Summary: Type Annotated Stubs for Autodesk Maya's python APIs
Home-page: https://www.github.com/Muream/maya-stubs
License: MIT
Keywords: stubs,autodesk,maya,cmds,OpenMaya
Author: Loïc Pinsard
Author-email: muream@gmail.com
Requires-Python: >=2.7, !=3.0.*, !=3.1.*, !=3.2.*, !=3.3.*, !=3.4.*, !=3.5.*, !=3.6.*
Classifier: License :: OSI Approved :: MIT License
Classifier: Programming Language :: Python :: 2
Classifier: Programming Language :: Python :: 2.7
Classifier: Programming Language :: Python :: 3
Classifier: Programming Language :: Python :: 3.7
Classifier: Programming Language :: Python :: 3.8
Classifier: Programming Language :: Python :: 3.9
Classifier: Programming Language :: Python :: 3.10
Classifier: Programming Language :: Python :: 3.11
Project-URL: Repository, https://www.github.com/Muream/maya-stubs
